{
	"info": {
		"description": "V2F_HY_9244_20210111_104742_N_CH1_Seoul_Cloud_Mainroad_Day_12750_BBOX JSON file",
		"url": "",
		"version": "1.0",
		"year": 2021,
		"contributor": "Konkuk_university",
		"date_created": "2021/05/12"
	},
	"images": {
		"file_name": "V2F_HY_9244_20210111_104742_N_CH1_Seoul_Cloud_Mainroad_Day_12750.png",
		"height": 720,
		"width": 1280,
		"id": 1
	},
	"annotations": [
		{
			"segmentation": [],
			"polyline": [],
			"image_id": 1,
			"bbox": [
				52.06012378426171,
				502.4933687002652,
				293.1211317418214,
				99.5932802829355
			],
			"category_id": 10,
			"area": 29192.89503041448,
			"is_crowd": 0,
			"id": 1
		},
		{
			"segmentation": [],
			"polyline": [],
			"image_id": 1,
			"bbox": [
				333.99981656424836,
				19.95780977712556,
				35.8066587177841,
				92.15812161790332
			],
			"category_id": 2,
			"area": 3299.8744088443054,
			"is_crowd": 0,
			"id": 2
		}
	],
	"categories": [
		{
			"id": 1,
			"name": "Animals(Dolls)"
		},
		{
			"id": 2,
			"name": "Person"
		},
		{
			"id": 3,
			"name": "Garbage bag & sacks"
		},
		{
			"id": 4,
			"name": "Construction signs & Parking prohibited board"
		},
		{
			"id": 5,
			"name": "Traffic cone"
		},
		{
			"id": 6,
			"name": "Box"
		},
		{
			"id": 7,
			"name": "Stones on road"
		},
		{
			"id": 8,
			"name": "Pothole on road"
		},
		{
			"id": 9,
			"name": "Filled pothole"
		},
		{
			"id": 10,
			"name": "Manhole"
		}
	]
}