{
	"info": {
		"description": "V3F_HY_9579_20160212_023850_E_CH0_Seoul_Sun_Mainroad_Sunset_14488_BBOX JSON file",
		"url": "",
		"version": "1.0",
		"year": 2021,
		"contributor": "Konkuk_university",
		"date_created": "2021/05/12"
	},
	"images": {
		"file_name": "V3F_HY_9579_20160212_023850_E_CH0_Seoul_Sun_Mainroad_Sunset_14488.png",
		"height": 720,
		"width": 1280,
		"id": 1
	},
	"annotations": [
		{
			"segmentation": [],
			"polyline": [],
			"image_id": 1,
			"bbox": [
				1230.0403768506058,
				184.33378196500675,
				31.009421265141327,
				67.18707940780618
			],
			"category_id": 2,
			"area": 2083.432448931164,
			"is_crowd": 0,
			"id": 1
		},
		{
			"segmentation": [],
			"polyline": [],
			"image_id": 1,
			"bbox": [
				1100.8344549125168,
				142.9878869448183,
				165.38358008075377,
				341.1036339165545
			],
			"category_id": 2,
			"area": 56412.94015567461,
			"is_crowd": 0,
			"id": 2
		},
		{
			"segmentation": [],
			"polyline": [],
			"image_id": 1,
			"bbox": [
				1007.8061911170928,
				173.99730820995964,
				62.01884253028254,
				129.20592193808884
			],
			"category_id": 2,
			"area": 8013.20172665831,
			"is_crowd": 0,
			"id": 3
		},
		{
			"segmentation": [],
			"polyline": [],
			"image_id": 1,
			"bbox": [
				790.7402422611036,
				184.33378196500675,
				51.682368775235545,
				113.70121130551816
			],
			"category_id": 2,
			"area": 5876.347932882771,
			"is_crowd": 0,
			"id": 4
		},
		{
			"segmentation": [],
			"polyline": [],
			"image_id": 1,
			"bbox": [
				640.8613728129206,
				86.13728129205923,
				160.21534320323008,
				465.1413189771198
			],
			"category_id": 2,
			"area": 74522.77605792237,
			"is_crowd": 0,
			"id": 5
		},
		{
			"segmentation": [],
			"polyline": [],
			"image_id": 1,
			"bbox": [
				413.45895020188425,
				168.8290713324361,
				93.02826379542398,
				242.90713324360695
			],
			"category_id": 2,
			"area": 22597.22886917647,
			"is_crowd": 0,
			"id": 6
		},
		{
			"segmentation": [],
			"polyline": [],
			"image_id": 1,
			"bbox": [
				248.07537012113056,
				158.49259757738898,
				93.02826379542398,
				294.5895020188425
			],
			"category_id": 2,
			"area": 27405.149905171464,
			"is_crowd": 0,
			"id": 7
		},
		{
			"segmentation": [],
			"polyline": [],
			"image_id": 1,
			"bbox": [
				160.21534320323016,
				158.49259757738898,
				103.36473755047106,
				263.58008075370117
			],
			"category_id": 2,
			"area": 27244.88587063829,
			"is_crowd": 0,
			"id": 8
		},
		{
			"segmentation": [],
			"polyline": [],
			"image_id": 1,
			"bbox": [
				5.168236877523554,
				199.8384925975774,
				41.34589502018843,
				165.38358008075377
			],
			"category_id": 2,
			"area": 6837.932140081772,
			"is_crowd": 0,
			"id": 9
		}
	],
	"categories": [
		{
			"id": 1,
			"name": "Animals(Dolls)"
		},
		{
			"id": 2,
			"name": "Person"
		},
		{
			"id": 3,
			"name": "Garbage bag & sacks"
		},
		{
			"id": 4,
			"name": "Construction signs & Parking prohibited board"
		},
		{
			"id": 5,
			"name": "Traffic cone"
		},
		{
			"id": 6,
			"name": "Box"
		},
		{
			"id": 7,
			"name": "Stones on road"
		},
		{
			"id": 8,
			"name": "Pothole on road"
		},
		{
			"id": 9,
			"name": "Filled pothole"
		},
		{
			"id": 10,
			"name": "Manhole"
		}
	]
}