{
	"info": {
		"description": "V3F_HY_8453_20201102_142133_E_CH0_Seoul_Sun_Mainroad_Sunset_44233_BBOX JSON file",
		"url": "",
		"version": "1.0",
		"year": 2021,
		"contributor": "Konkuk_university",
		"date_created": "2021/05/12"
	},
	"images": {
		"file_name": "V3F_HY_8453_20201102_142133_E_CH0_Seoul_Sun_Mainroad_Sunset_44233.png",
		"height": 720,
		"width": 1281,
		"id": 1
	},
	"annotations": [
		{
			"segmentation": [],
			"polyline": [],
			"image_id": 1,
			"bbox": [
				1241.7742047776817,
				195.1584301551743,
				36.723360513070475,
				116.9901342059244
			],
			"category_id": 2,
			"area": 4296.2708749166595,
			"is_crowd": 0,
			"id": 1
		},
		{
			"segmentation": [],
			"polyline": [],
			"image_id": 1,
			"bbox": [
				1079.666799084271,
				184.1414220012532,
				24.657113487347488,
				96.52997620578518
			],
			"category_id": 2,
			"area": 2380.1505782369977,
			"is_crowd": 0,
			"id": 2
		},
		{
			"segmentation": [],
			"polyline": [],
			"image_id": 1,
			"bbox": [
				34.54735690794813,
				200.56659982669888,
				31.668410498952458,
				25.2707518122954
			],
			"category_id": 6,
			"area": 800.2845420089176,
			"is_crowd": 0,
			"id": 3
		}
	],
	"categories": [
		{
			"id": 1,
			"name": "Animals(Dolls)"
		},
		{
			"id": 2,
			"name": "Person"
		},
		{
			"id": 3,
			"name": "Garbage bag & sacks"
		},
		{
			"id": 4,
			"name": "Construction signs & Parking prohibited board"
		},
		{
			"id": 5,
			"name": "Traffic cone"
		},
		{
			"id": 6,
			"name": "Box"
		},
		{
			"id": 7,
			"name": "Stones on road"
		},
		{
			"id": 8,
			"name": "Pothole on road"
		},
		{
			"id": 9,
			"name": "Filled pothole"
		},
		{
			"id": 10,
			"name": "Manhole"
		}
	]
}