{
	"info": {
		"description": "V3F_HY_9892_20160212_020020_N_CH1_Seoul_Sun_Mainroad_Day_73274_BBOX JSON file",
		"url": "",
		"version": "1.0",
		"year": 2021,
		"contributor": "Konkuk_university",
		"date_created": "2021/05/12"
	},
	"images": {
		"file_name": "V3F_HY_9892_20160212_020020_N_CH1_Seoul_Sun_Mainroad_Day_73274.png",
		"height": 720,
		"width": 1280,
		"id": 1
	},
	"annotations": [
		{
			"segmentation": [],
			"polyline": [],
			"image_id": 1,
			"bbox": [
				1242.2619047619048,
				76.19047619047619,
				37.738095238095184,
				31.54761904761905
			],
			"category_id": 7,
			"area": 1190.5470521541934,
			"is_crowd": 0,
			"id": 1
		},
		{
			"segmentation": [],
			"polyline": [],
			"image_id": 1,
			"bbox": [
				1250.595238095238,
				43.45238095238096,
				29.404761904761926,
				33.333333333333336
			],
			"category_id": 7,
			"area": 980.1587301587309,
			"is_crowd": 0,
			"id": 2
		},
		{
			"segmentation": [],
			"polyline": [],
			"image_id": 1,
			"bbox": [
				1181.547619047619,
				82.14285714285714,
				60.119047619047706,
				30.35714285714286
			],
			"category_id": 7,
			"area": 1825.0425170068056,
			"is_crowd": 0,
			"id": 3
		},
		{
			"segmentation": [],
			"polyline": [],
			"image_id": 1,
			"bbox": [
				1222.0238095238096,
				46.42857142857143,
				29.76190476190459,
				37.5
			],
			"category_id": 7,
			"area": 1116.071428571422,
			"is_crowd": 0,
			"id": 4
		},
		{
			"segmentation": [],
			"polyline": [],
			"image_id": 1,
			"bbox": [
				1170.8333333333337,
				51.19047619047619,
				51.19047619047615,
				42.85714285714286
			],
			"category_id": 7,
			"area": 2193.8775510204064,
			"is_crowd": 0,
			"id": 5
		},
		{
			"segmentation": [],
			"polyline": [],
			"image_id": 1,
			"bbox": [
				1126.190476190476,
				46.42857142857143,
				53.57142857142867,
				41.07142857142857
			],
			"category_id": 7,
			"area": 2200.25510204082,
			"is_crowd": 0,
			"id": 6
		},
		{
			"segmentation": [],
			"polyline": [],
			"image_id": 1,
			"bbox": [
				1142.857142857143,
				78.57142857142857,
				39.880952380952294,
				36.30952380952381
			],
			"category_id": 7,
			"area": 1448.0583900226727,
			"is_crowd": 0,
			"id": 7
		},
		{
			"segmentation": [],
			"polyline": [],
			"image_id": 1,
			"bbox": [
				1095.8333333333337,
				63.095238095238095,
				48.809523809523625,
				51.785714285714285
			],
			"category_id": 7,
			"area": 2527.636054421759,
			"is_crowd": 0,
			"id": 8
		},
		{
			"segmentation": [],
			"polyline": [],
			"image_id": 1,
			"bbox": [
				1047.6190476190477,
				47.023809523809526,
				52.380952380952294,
				65.47619047619048
			],
			"category_id": 7,
			"area": 3429.7052154194957,
			"is_crowd": 0,
			"id": 9
		},
		{
			"segmentation": [],
			"polyline": [],
			"image_id": 1,
			"bbox": [
				1021.4285714285714,
				76.78571428571429,
				33.33333333333337,
				36.9047619047619
			],
			"category_id": 7,
			"area": 1230.1587301587313,
			"is_crowd": 0,
			"id": 10
		},
		{
			"segmentation": [],
			"polyline": [],
			"image_id": 1,
			"bbox": [
				988.6904761904764,
				73.21428571428572,
				45.2380952380953,
				41.07142857142857
			],
			"category_id": 7,
			"area": 1857.9931972789138,
			"is_crowd": 0,
			"id": 11
		},
		{
			"segmentation": [],
			"polyline": [],
			"image_id": 1,
			"bbox": [
				998.809523809524,
				50,
				37.5,
				27.97619047619048
			],
			"category_id": 7,
			"area": 1049.1071428571431,
			"is_crowd": 0,
			"id": 12
		},
		{
			"segmentation": [],
			"polyline": [],
			"image_id": 1,
			"bbox": [
				956.547619047619,
				84.52380952380953,
				34.52380952380952,
				26.78571428571428
			],
			"category_id": 7,
			"area": 924.7448979591834,
			"is_crowd": 0,
			"id": 13
		},
		{
			"segmentation": [],
			"polyline": [],
			"image_id": 1,
			"bbox": [
				967.2619047619048,
				54.761904761904766,
				25.595238095238074,
				29.761904761904766
			],
			"category_id": 7,
			"area": 761.7630385487523,
			"is_crowd": 0,
			"id": 14
		},
		{
			"segmentation": [],
			"polyline": [],
			"image_id": 1,
			"bbox": [
				931.547619047619,
				58.333333333333336,
				35.71428571428578,
				56.54761904761904
			],
			"category_id": 7,
			"area": 2019.557823129255,
			"is_crowd": 0,
			"id": 15
		},
		{
			"segmentation": [],
			"polyline": [],
			"image_id": 1,
			"bbox": [
				897.0238095238095,
				82.14285714285714,
				35.119047619047706,
				23.21428571428572
			],
			"category_id": 7,
			"area": 815.263605442179,
			"is_crowd": 0,
			"id": 16
		},
		{
			"segmentation": [],
			"polyline": [],
			"image_id": 1,
			"bbox": [
				924.404761904762,
				52.38095238095238,
				29.16666666666663,
				33.33333333333334
			],
			"category_id": 7,
			"area": 972.2222222222213,
			"is_crowd": 0,
			"id": 17
		},
		{
			"segmentation": [],
			"polyline": [],
			"image_id": 1,
			"bbox": [
				872.6190476190477,
				55.95238095238096,
				53.571428571428555,
				55.357142857142854
			],
			"category_id": 7,
			"area": 2965.5612244897948,
			"is_crowd": 0,
			"id": 18
		},
		{
			"segmentation": [],
			"polyline": [],
			"image_id": 1,
			"bbox": [
				836.9047619047619,
				70.83333333333334,
				38.69047619047615,
				38.69047619047619
			],
			"category_id": 7,
			"area": 1496.9529478458032,
			"is_crowd": 0,
			"id": 19
		},
		{
			"segmentation": [],
			"polyline": [],
			"image_id": 1,
			"bbox": [
				804.7619047619048,
				54.16666666666667,
				68.45238095238096,
				63.69047619047619
			],
			"category_id": 7,
			"area": 4359.7647392290255,
			"is_crowd": 0,
			"id": 20
		},
		{
			"segmentation": [],
			"polyline": [],
			"image_id": 1,
			"bbox": [
				748.8095238095239,
				79.16666666666667,
				55.95238095238096,
				35.11904761904762
			],
			"category_id": 7,
			"area": 1964.99433106576,
			"is_crowd": 0,
			"id": 21
		},
		{
			"segmentation": [],
			"polyline": [],
			"image_id": 1,
			"bbox": [
				780.952380952381,
				67.26190476190476,
				29.166666666666742,
				32.14285714285715
			],
			"category_id": 7,
			"area": 937.5000000000027,
			"is_crowd": 0,
			"id": 22
		},
		{
			"segmentation": [],
			"polyline": [],
			"image_id": 1,
			"bbox": [
				771.4285714285714,
				52.97619047619048,
				30.952380952380963,
				23.80952380952381
			],
			"category_id": 7,
			"area": 736.9614512471658,
			"is_crowd": 0,
			"id": 23
		},
		{
			"segmentation": [],
			"polyline": [],
			"image_id": 1,
			"bbox": [
				730.3571428571429,
				76.78571428571429,
				24.404761904761926,
				32.73809523809524
			],
			"category_id": 7,
			"area": 798.9654195011345,
			"is_crowd": 0,
			"id": 24
		},
		{
			"segmentation": [],
			"polyline": [],
			"image_id": 1,
			"bbox": [
				706.547619047619,
				66.07142857142857,
				27.380952380952408,
				41.66666666666667
			],
			"category_id": 7,
			"area": 1140.873015873017,
			"is_crowd": 0,
			"id": 25
		},
		{
			"segmentation": [],
			"polyline": [],
			"image_id": 1,
			"bbox": [
				693.452380952381,
				86.90476190476191,
				24.404761904761926,
				26.78571428571428
			],
			"category_id": 7,
			"area": 653.6989795918372,
			"is_crowd": 0,
			"id": 26
		},
		{
			"segmentation": [],
			"polyline": [],
			"image_id": 1,
			"bbox": [
				681.547619047619,
				76.19047619047619,
				22.619047619047706,
				32.73809523809524
			],
			"category_id": 7,
			"area": 740.5045351473951,
			"is_crowd": 0,
			"id": 27
		},
		{
			"segmentation": [],
			"polyline": [],
			"image_id": 1,
			"bbox": [
				727.9761904761905,
				63.095238095238095,
				41.66666666666674,
				18.452380952380956
			],
			"category_id": 7,
			"area": 768.8492063492079,
			"is_crowd": 0,
			"id": 28
		}
	],
	"categories": [
		{
			"id": 1,
			"name": "Animals(Dolls)"
		},
		{
			"id": 2,
			"name": "Person"
		},
		{
			"id": 3,
			"name": "Garbage bag & sacks"
		},
		{
			"id": 4,
			"name": "Construction signs & Parking prohibited board"
		},
		{
			"id": 5,
			"name": "Traffic cone"
		},
		{
			"id": 6,
			"name": "Box"
		},
		{
			"id": 7,
			"name": "Stones on road"
		},
		{
			"id": 8,
			"name": "Pothole on road"
		},
		{
			"id": 9,
			"name": "Filled pothole"
		},
		{
			"id": 10,
			"name": "Manhole"
		}
	]
}