{
	"info": {
		"description": "V3F_HY_9965_20160212_024250_N_CH0_Seoul_Sun_Mainroad_Day_51804_BBOX JSON file",
		"url": "",
		"version": "1.0",
		"year": 2021,
		"contributor": "Konkuk_university",
		"date_created": "2021/05/12"
	},
	"images": {
		"file_name": "V3F_HY_9965_20160212_024250_N_CH0_Seoul_Sun_Mainroad_Day_51804.png",
		"height": 720,
		"width": 1280,
		"id": 1
	},
	"annotations": [
		{
			"segmentation": [],
			"polyline": [],
			"image_id": 1,
			"bbox": [
				871.4285714285714,
				266.07142857142856,
				29.16666666666663,
				39.285714285714334
			],
			"category_id": 1,
			"area": 1145.8333333333333,
			"is_crowd": 0,
			"id": 1
		},
		{
			"segmentation": [],
			"polyline": [],
			"image_id": 1,
			"bbox": [
				933.3333333333334,
				120.83333333333334,
				100.00000000000011,
				239.8809523809524
			],
			"category_id": 2,
			"area": 23988.09523809527,
			"is_crowd": 0,
			"id": 2
		},
		{
			"segmentation": [],
			"polyline": [],
			"image_id": 1,
			"bbox": [
				266.8508287292818,
				413.2596685082873,
				52.486187845303846,
				7.1823204419889635
			],
			"category_id": 10,
			"area": 376.97261988339847,
			"is_crowd": 0,
			"id": 3
		},
		{
			"segmentation": [],
			"polyline": [],
			"image_id": 1,
			"bbox": [
				558.1749049429658,
				203.42205323193917,
				21.673003802281418,
				46.00760456273764
			],
			"category_id": 2,
			"area": 997.1229886220727,
			"is_crowd": 0,
			"id": 4
		}
	],
	"categories": [
		{
			"id": 1,
			"name": "Animals(Dolls)"
		},
		{
			"id": 2,
			"name": "Person"
		},
		{
			"id": 3,
			"name": "Garbage bag & sacks"
		},
		{
			"id": 4,
			"name": "Construction signs & Parking prohibited board"
		},
		{
			"id": 5,
			"name": "Traffic cone"
		},
		{
			"id": 6,
			"name": "Box"
		},
		{
			"id": 7,
			"name": "Stones on road"
		},
		{
			"id": 8,
			"name": "Pothole on road"
		},
		{
			"id": 9,
			"name": "Filled pothole"
		},
		{
			"id": 10,
			"name": "Manhole"
		}
	]
}